rap_utils/__init__.py
rap_utils/petl/adapters/__init__.py
rap_utils/petl/adapters/airtable.py
rap_utils/petl/adapters/google_analytics.py
rap_utils/petl/adapters/one_drive.py
rap_utils/petl/adapters/sftp.py
rap_utils/petl/adapters/spektrix.py
rap_utils/petl/io/parquet_view.py
rap_utils/runner/__init__.py
rap_utils/runner/__main__.py
rap_utils/runner/log.py
rap_utils/runner/run.py
rap_utils-0.0.10.dist-info/METADATA
rap_utils-0.0.10.dist-info/WHEEL
rap_utils-0.0.10.dist-info/licenses/LICENSE
rap_utils-0.0.10.dist-info/RECORD
